orangecontrib/__init__.py
orangecontrib/orange3_fca/__init__.py
orangecontrib/orange3_fca/widgets/OWDatasampler.py
orangecontrib/orange3_fca/widgets/__init__.py
orangecontrib/orange3_fca/widgets/icons/DataSampler.svg
orange3_fca_addon-0.0.4.dist-info/LICENSE
orange3_fca_addon-0.0.4.dist-info/METADATA
orange3_fca_addon-0.0.4.dist-info/WHEEL
orange3_fca_addon-0.0.4.dist-info/entry_points.txt
orange3_fca_addon-0.0.4.dist-info/top_level.txt
orange3_fca_addon-0.0.4.dist-info/RECORD
