Metadata-Version: 2.1
Name: orange3-fca-addon
Version: 0.0.4
Summary: Orange FCA add-on for Orange data mining software package.
Author-email: jesus laime <laimejesu@gmail.com>
License: GNU GENERAL PUBLIC LICENSE
Project-URL: Homepage, https://github.com/LaimeJesus/orange3-fca-addon
Keywords: orange3 add-on
Classifier: Development Status :: 1 - Planning
Classifier: Programming Language :: Python
Classifier: Programming Language :: Python :: 3 :: Only
Classifier: Programming Language :: Python :: 3.7
Classifier: Programming Language :: Python :: 3.8
Classifier: Programming Language :: Python :: 3.9
Classifier: Programming Language :: Python :: 3.10
Classifier: License :: OSI Approved :: GNU General Public License v3 or later (GPLv3+)
Classifier: Operating System :: OS Independent
Classifier: Topic :: Scientific/Engineering :: Artificial Intelligence
Classifier: Topic :: Software Development :: Libraries :: Python Modules
Classifier: Intended Audience :: Education
Classifier: Intended Audience :: Science/Research
Classifier: Intended Audience :: Developers
Requires-Python: >=3.7
License-File: LICENSE
Requires-Dist: Orange3 (>=3.31)
Requires-Dist: orange-widget-base (>=4.21.0)
Requires-Dist: orange-canvas-core (>=0.1.31)
